tlalocesmcp/__main__.py
tlalocesmcp/file_handler.py
tlaloc_es_mcp-0.1.6.dist-info/METADATA
tlaloc_es_mcp-0.1.6.dist-info/WHEEL
tlaloc_es_mcp-0.1.6.dist-info/entry_points.txt
tlaloc_es_mcp-0.1.6.dist-info/top_level.txt
tlaloc_es_mcp-0.1.6.dist-info/RECORD
