Metadata-Version: 2.4
Name: tlaloc-es-mcp
Version: 0.1.6
Summary: Add your description here
Requires-Python: >=3.12
Requires-Dist: click>=8.2.0
Requires-Dist: mcp[cli]>=1.8.1
Requires-Dist: poethepoet>=0.34.0
